lfpreviewer/scaling.py
lfpreviewer/__init__.py
lfpreviewer/terminal.py
lfpreviewer/layer.py
lfpreviewer/xutil.py
lfpreviewer/batch.py
lfpreviewer/version.py
lfpreviewer/process.py
lfpreviewer/tmux_util.py
lfpreviewer/ui.py
lfpreviewer/geometry.py
lfpreviewer/__main__.py
lfpreviewer/files.py
lfpreviewer/loading.py
lfpreviewer/pattern.py
lfpreviewer/action.py
lfpreviewer/parser.py
lfpreviewer/X.cpython-311-x86_64-linux-gnu.so
lfpreviewer/thread.py
lfpreviewer/conversion.py
lfpreviewer/query_windows.py
lfpreviewer/library.py
lfpreviewer/X/Xshm.c
lfpreviewer/X/X.c
lfpreviewer/X/display.c
lfpreviewer/X/window.c
lfpreviewer/lib/__init__.py
lfpreviewer/lib/lib.sh
lfpreviewer/lib/v0/__init__.py
lfpreviewer.libs/libXRes-4652b135.so.1.0.0
lfpreviewer-1.0.0.dist-info/WHEEL
lfpreviewer-1.0.0.dist-info/RECORD
lfpreviewer-1.0.0.dist-info/top_level.txt
lfpreviewer-1.0.0.dist-info/METADATA
lfpreviewer-1.0.0.dist-info/entry_points.txt
