Metadata-Version: 2.1
Name: lfpreviewer
Version: 1.0.0
Summary: Image Previewer for LFP
License: GPLv3
Classifier: Environment :: Console
Classifier: Environment :: X11 Applications
Classifier: Operating System :: POSIX :: Linux
Requires-Python: >=3.6
Requires-Dist: docopt
Requires-Dist: attrs >=18.2.0
Requires-Dist: pillow
